<?xml version="1.0" ?>
<annotation>
   <folder/>
   <filename>AAPL_2003_page_67_table_0.jpg</filename>
   <path>AAPL_2003_page_67_table_0.jpg</path>
   <source>
      <database>FinTabNet.c-Structure</database>
   </source>
   <size>
      <width>644</width>
      <height>276</height>
      <depth>3</depth>
   </size>
   <segmented>0</segmented>
   <object>
      <name>table</name>
      <pose>Frontal</pose>
      <truncated>0</truncated>
      <difficult>0</difficult>
      <occluded>0</occluded>
      <bndbox>
         <xmin>28.575757575757567</xmin>
         <ymin>29.203115135732332</ymin>
         <xmax>613.2008475872001</xmax>
         <ymax>245.20591658775243</ymax>
      </bndbox>
   </object>
   <object>
      <name>table spanning cell</name>
      <pose>Frontal</pose>
      <truncated>0</truncated>
      <difficult>0</difficult>
      <occluded>0</occluded>
      <bndbox>
         <xmin>140.31791209211252</xmin>
         <ymin>29.203115135732332</ymin>
         <xmax>434.5101010101009</xmax>
         <ymax>50.71461687184342</ymax>
      </bndbox>
   </object>
   <object>
      <name>table spanning cell</name>
      <pose>Frontal</pose>
      <truncated>0</truncated>
      <difficult>0</difficult>
      <occluded>0</occluded>
      <bndbox>
         <xmin>434.5101010101009</xmin>
         <ymin>29.203115135732332</ymin>
         <xmax>613.2008475872001</xmax>
         <ymax>50.71461687184342</ymax>
      </bndbox>
   </object>
   <object>
      <name>table column header</name>
      <pose>Frontal</pose>
      <truncated>0</truncated>
      <difficult>0</difficult>
      <occluded>0</occluded>
      <bndbox>
         <xmin>28.575757575757567</xmin>
         <ymin>29.203115135732332</ymin>
         <xmax>613.2008475872001</xmax>
         <ymax>135.94188959911617</ymax>
      </bndbox>
   </object>
   <object>
      <name>table row</name>
      <pose>Frontal</pose>
      <truncated>0</truncated>
      <difficult>0</difficult>
      <occluded>0</occluded>
      <bndbox>
         <xmin>28.575757575757567</xmin>
         <ymin>29.203115135732332</ymin>
         <xmax>613.2008475872001</xmax>
         <ymax>50.71461687184342</ymax>
      </bndbox>
   </object>
   <object>
      <name>table row</name>
      <pose>Frontal</pose>
      <truncated>0</truncated>
      <difficult>0</difficult>
      <occluded>0</occluded>
      <bndbox>
         <xmin>28.575757575757567</xmin>
         <ymin>50.71461687184342</ymin>
         <xmax>613.2008475872001</xmax>
         <ymax>135.94188959911617</ymax>
      </bndbox>
   </object>
   <object>
      <name>table row</name>
      <pose>Frontal</pose>
      <truncated>0</truncated>
      <difficult>0</difficult>
      <occluded>0</occluded>
      <bndbox>
         <xmin>28.575757575757567</xmin>
         <ymin>135.94188959911617</ymin>
         <xmax>613.2008475872001</xmax>
         <ymax>158.03784919507575</ymax>
      </bndbox>
   </object>
   <object>
      <name>table row</name>
      <pose>Frontal</pose>
      <truncated>0</truncated>
      <difficult>0</difficult>
      <occluded>0</occluded>
      <bndbox>
         <xmin>28.575757575757567</xmin>
         <ymin>158.03784919507575</ymin>
         <xmax>613.2008475872001</xmax>
         <ymax>171.92673808396455</ymax>
      </bndbox>
   </object>
   <object>
      <name>table row</name>
      <pose>Frontal</pose>
      <truncated>0</truncated>
      <difficult>0</difficult>
      <occluded>0</occluded>
      <bndbox>
         <xmin>28.575757575757567</xmin>
         <ymin>171.92673808396455</ymin>
         <xmax>613.2008475872001</xmax>
         <ymax>185.81562697285347</ymax>
      </bndbox>
   </object>
   <object>
      <name>table row</name>
      <pose>Frontal</pose>
      <truncated>0</truncated>
      <difficult>0</difficult>
      <occluded>0</occluded>
      <bndbox>
         <xmin>28.575757575757567</xmin>
         <ymin>185.81562697285347</ymin>
         <xmax>613.2008475872001</xmax>
         <ymax>199.70451586174238</ymax>
      </bndbox>
   </object>
   <object>
      <name>table row</name>
      <pose>Frontal</pose>
      <truncated>0</truncated>
      <difficult>0</difficult>
      <occluded>0</occluded>
      <bndbox>
         <xmin>28.575757575757567</xmin>
         <ymin>199.70451586174238</ymin>
         <xmax>613.2008475872001</xmax>
         <ymax>213.5934047506313</ymax>
      </bndbox>
   </object>
   <object>
      <name>table row</name>
      <pose>Frontal</pose>
      <truncated>0</truncated>
      <difficult>0</difficult>
      <occluded>0</occluded>
      <bndbox>
         <xmin>28.575757575757567</xmin>
         <ymin>213.5934047506313</ymin>
         <xmax>613.2008475872001</xmax>
         <ymax>229.37623303345958</ymax>
      </bndbox>
   </object>
   <object>
      <name>table row</name>
      <pose>Frontal</pose>
      <truncated>0</truncated>
      <difficult>0</difficult>
      <occluded>0</occluded>
      <bndbox>
         <xmin>28.575757575757567</xmin>
         <ymin>229.37623303345958</ymin>
         <xmax>613.2008475872001</xmax>
         <ymax>245.20591658775243</ymax>
      </bndbox>
   </object>
   <object>
      <name>table column</name>
      <pose>Frontal</pose>
      <truncated>0</truncated>
      <difficult>0</difficult>
      <occluded>0</occluded>
      <bndbox>
         <xmin>28.575757575757567</xmin>
         <ymin>29.203115135732332</ymin>
         <xmax>140.3179217251864</xmax>
         <ymax>245.20591658775243</ymax>
      </bndbox>
   </object>
   <object>
      <name>table column</name>
      <pose>Frontal</pose>
      <truncated>0</truncated>
      <difficult>0</difficult>
      <occluded>0</occluded>
      <bndbox>
         <xmin>140.3179217251864</xmin>
         <ymin>29.203115135732332</ymin>
         <xmax>263.4239919643209</xmax>
         <ymax>245.20591658775243</ymax>
      </bndbox>
   </object>
   <object>
      <name>table column</name>
      <pose>Frontal</pose>
      <truncated>0</truncated>
      <difficult>0</difficult>
      <occluded>0</occluded>
      <bndbox>
         <xmin>263.4239919643209</xmin>
         <ymin>29.203115135732332</ymin>
         <xmax>353.70912941056065</xmax>
         <ymax>245.20591658775243</ymax>
      </bndbox>
   </object>
   <object>
      <name>table column</name>
      <pose>Frontal</pose>
      <truncated>0</truncated>
      <difficult>0</difficult>
      <occluded>0</occluded>
      <bndbox>
         <xmin>353.70912941056065</xmin>
         <ymin>29.203115135732332</ymin>
         <xmax>434.5101202762488</xmax>
         <ymax>245.20591658775243</ymax>
      </bndbox>
   </object>
   <object>
      <name>table column</name>
      <pose>Frontal</pose>
      <truncated>0</truncated>
      <difficult>0</difficult>
      <occluded>0</occluded>
      <bndbox>
         <xmin>434.5101202762488</xmin>
         <ymin>29.203115135732332</ymin>
         <xmax>544.3587207216204</xmax>
         <ymax>245.20591658775243</ymax>
      </bndbox>
   </object>
   <object>
      <name>table column</name>
      <pose>Frontal</pose>
      <truncated>0</truncated>
      <difficult>0</difficult>
      <occluded>0</occluded>
      <bndbox>
         <xmin>544.3587207216204</xmin>
         <ymin>29.203115135732332</ymin>
         <xmax>613.2008475872001</xmax>
         <ymax>245.20591658775243</ymax>
      </bndbox>
   </object>
</annotation>
