<?xml version="1.0" ?>
<annotation>
   <folder/>
   <filename>GS_2012_page_112_table_0.jpg</filename>
   <path>GS_2012_page_112_table_0.jpg</path>
   <source>
      <database>FinTabNet.c-Structure</database>
   </source>
   <size>
      <width>730</width>
      <height>657</height>
      <depth>3</depth>
   </size>
   <segmented>0</segmented>
   <object>
      <name>table</name>
      <pose>Frontal</pose>
      <truncated>0</truncated>
      <difficult>0</difficult>
      <occluded>0</occluded>
      <bndbox>
         <xmin>28.94661084171456</xmin>
         <ymin>29.362660842837045</ymin>
         <xmax>698.540314695083</xmax>
         <ymax>626.0408185664113</ymax>
      </bndbox>
   </object>
   <object>
      <name>table spanning cell</name>
      <pose>Frontal</pose>
      <truncated>0</truncated>
      <difficult>0</difficult>
      <occluded>0</occluded>
      <bndbox>
         <xmin>28.94661084171456</xmin>
         <ymin>29.362660842837045</ymin>
         <xmax>484.76261424409324</xmax>
         <ymax>58.82881486096144</ymax>
      </bndbox>
   </object>
   <object>
      <name>table spanning cell</name>
      <pose>Frontal</pose>
      <truncated>0</truncated>
      <difficult>0</difficult>
      <occluded>0</occluded>
      <bndbox>
         <xmin>484.76261424409324</xmin>
         <ymin>29.362660842837045</ymin>
         <xmax>698.540314695083</xmax>
         <ymax>43.05933381101333</ymax>
      </bndbox>
   </object>
   <object>
      <name>table projected row header</name>
      <pose>Frontal</pose>
      <truncated>0</truncated>
      <difficult>0</difficult>
      <occluded>0</occluded>
      <bndbox>
         <xmin>28.94661084171456</xmin>
         <ymin>58.82881486096144</ymin>
         <xmax>698.540314695083</xmax>
         <ymax>73.25920562939018</ymax>
      </bndbox>
   </object>
   <object>
      <name>table projected row header</name>
      <pose>Frontal</pose>
      <truncated>0</truncated>
      <difficult>0</difficult>
      <occluded>0</occluded>
      <bndbox>
         <xmin>28.94661084171456</xmin>
         <ymin>128.91182890949275</ymin>
         <xmax>698.540314695083</xmax>
         <ymax>142.22472287076948</ymax>
      </bndbox>
   </object>
   <object>
      <name>table projected row header</name>
      <pose>Frontal</pose>
      <truncated>0</truncated>
      <difficult>0</difficult>
      <occluded>0</occluded>
      <bndbox>
         <xmin>28.94661084171456</xmin>
         <ymin>183.82881486096144</ymin>
         <xmax>698.540314695083</xmax>
         <ymax>197.14170882223817</ymax>
      </bndbox>
   </object>
   <object>
      <name>table projected row header</name>
      <pose>Frontal</pose>
      <truncated>0</truncated>
      <difficult>0</difficult>
      <occluded>0</occluded>
      <bndbox>
         <xmin>28.94661084171456</xmin>
         <ymin>280.8913751945642</ymin>
         <xmax>698.540314695083</xmax>
         <ymax>294.2042886434387</ymax>
      </bndbox>
   </object>
   <object>
      <name>table projected row header</name>
      <pose>Frontal</pose>
      <truncated>0</truncated>
      <difficult>0</difficult>
      <occluded>0</occluded>
      <bndbox>
         <xmin>28.94661084171456</xmin>
         <ymin>406.0510175955859</ymin>
         <xmax>698.540314695083</xmax>
         <ymax>419.3639310444604</ymax>
      </bndbox>
   </object>
   <object>
      <name>table projected row header</name>
      <pose>Frontal</pose>
      <truncated>0</truncated>
      <difficult>0</difficult>
      <occluded>0</occluded>
      <bndbox>
         <xmin>28.94661084171456</xmin>
         <ymin>489.06506612687576</ymin>
         <xmax>698.540314695083</xmax>
         <ymax>502.3779795757504</ymax>
      </bndbox>
   </object>
   <object>
      <name>table projected row header</name>
      <pose>Frontal</pose>
      <truncated>0</truncated>
      <difficult>0</difficult>
      <occluded>0</occluded>
      <bndbox>
         <xmin>28.94661084171456</xmin>
         <ymin>543.9820520783445</ymin>
         <xmax>698.540314695083</xmax>
         <ymax>557.294965527219</ymax>
      </bndbox>
   </object>
   <object>
      <name>table column header</name>
      <pose>Frontal</pose>
      <truncated>0</truncated>
      <difficult>0</difficult>
      <occluded>0</occluded>
      <bndbox>
         <xmin>28.94661084171456</xmin>
         <ymin>29.362660842837045</ymin>
         <xmax>698.540314695083</xmax>
         <ymax>58.82881486096144</ymax>
      </bndbox>
   </object>
   <object>
      <name>table row</name>
      <pose>Frontal</pose>
      <truncated>0</truncated>
      <difficult>0</difficult>
      <occluded>0</occluded>
      <bndbox>
         <xmin>28.94661084171456</xmin>
         <ymin>29.362660842837045</ymin>
         <xmax>698.540314695083</xmax>
         <ymax>43.05933868291278</ymax>
      </bndbox>
   </object>
   <object>
      <name>table row</name>
      <pose>Frontal</pose>
      <truncated>0</truncated>
      <difficult>0</difficult>
      <occluded>0</occluded>
      <bndbox>
         <xmin>28.94661084171456</xmin>
         <ymin>43.05933868291278</ymin>
         <xmax>698.540314695083</xmax>
         <ymax>58.82881486096144</ymax>
      </bndbox>
   </object>
   <object>
      <name>table row</name>
      <pose>Frontal</pose>
      <truncated>0</truncated>
      <difficult>0</difficult>
      <occluded>0</occluded>
      <bndbox>
         <xmin>28.94661084171456</xmin>
         <ymin>58.82881486096144</ymin>
         <xmax>698.540314695083</xmax>
         <ymax>73.25921050128963</ymax>
      </bndbox>
   </object>
   <object>
      <name>table row</name>
      <pose>Frontal</pose>
      <truncated>0</truncated>
      <difficult>0</difficult>
      <occluded>0</occluded>
      <bndbox>
         <xmin>28.94661084171456</xmin>
         <ymin>73.25921050128963</ymin>
         <xmax>698.540314695083</xmax>
         <ymax>86.66917218711336</ymax>
      </bndbox>
   </object>
   <object>
      <name>table row</name>
      <pose>Frontal</pose>
      <truncated>0</truncated>
      <difficult>0</difficult>
      <occluded>0</occluded>
      <bndbox>
         <xmin>28.94661084171456</xmin>
         <ymin>86.66917218711336</ymin>
         <xmax>698.540314695083</xmax>
         <ymax>100.71769860512454</ymax>
      </bndbox>
   </object>
   <object>
      <name>table row</name>
      <pose>Frontal</pose>
      <truncated>0</truncated>
      <difficult>0</difficult>
      <occluded>0</occluded>
      <bndbox>
         <xmin>28.94661084171456</xmin>
         <ymin>100.71769860512454</ymin>
         <xmax>698.540314695083</xmax>
         <ymax>114.76622989503514</ymax>
      </bndbox>
   </object>
   <object>
      <name>table row</name>
      <pose>Frontal</pose>
      <truncated>0</truncated>
      <difficult>0</difficult>
      <occluded>0</occluded>
      <bndbox>
         <xmin>28.94661084171456</xmin>
         <ymin>114.76622989503514</ymin>
         <xmax>698.540314695083</xmax>
         <ymax>128.91182890949275</ymax>
      </bndbox>
   </object>
   <object>
      <name>table row</name>
      <pose>Frontal</pose>
      <truncated>0</truncated>
      <difficult>0</difficult>
      <occluded>0</occluded>
      <bndbox>
         <xmin>28.94661084171456</xmin>
         <ymin>128.91182890949275</ymin>
         <xmax>698.540314695083</xmax>
         <ymax>142.22472287076948</ymax>
      </bndbox>
   </object>
   <object>
      <name>table row</name>
      <pose>Frontal</pose>
      <truncated>0</truncated>
      <difficult>0</difficult>
      <occluded>0</occluded>
      <bndbox>
         <xmin>28.94661084171456</xmin>
         <ymin>142.22472287076948</ymin>
         <xmax>698.540314695083</xmax>
         <ymax>155.63468455659324</ymax>
      </bndbox>
   </object>
   <object>
      <name>table row</name>
      <pose>Frontal</pose>
      <truncated>0</truncated>
      <difficult>0</difficult>
      <occluded>0</occluded>
      <bndbox>
         <xmin>28.94661084171456</xmin>
         <ymin>155.63468455659324</ymin>
         <xmax>698.540314695083</xmax>
         <ymax>169.68321584650383</ymax>
      </bndbox>
   </object>
   <object>
      <name>table row</name>
      <pose>Frontal</pose>
      <truncated>0</truncated>
      <difficult>0</difficult>
      <occluded>0</occluded>
      <bndbox>
         <xmin>28.94661084171456</xmin>
         <ymin>169.68321584650383</ymin>
         <xmax>698.540314695083</xmax>
         <ymax>183.82881486096144</ymax>
      </bndbox>
   </object>
   <object>
      <name>table row</name>
      <pose>Frontal</pose>
      <truncated>0</truncated>
      <difficult>0</difficult>
      <occluded>0</occluded>
      <bndbox>
         <xmin>28.94661084171456</xmin>
         <ymin>183.82881486096144</ymin>
         <xmax>698.540314695083</xmax>
         <ymax>197.14170882223817</ymax>
      </bndbox>
   </object>
   <object>
      <name>table row</name>
      <pose>Frontal</pose>
      <truncated>0</truncated>
      <difficult>0</difficult>
      <occluded>0</occluded>
      <bndbox>
         <xmin>28.94661084171456</xmin>
         <ymin>197.14170882223817</ymin>
         <xmax>698.540314695083</xmax>
         <ymax>210.55167050806193</ymax>
      </bndbox>
   </object>
   <object>
      <name>table row</name>
      <pose>Frontal</pose>
      <truncated>0</truncated>
      <difficult>0</difficult>
      <occluded>0</occluded>
      <bndbox>
         <xmin>28.94661084171456</xmin>
         <ymin>210.55167050806193</ymin>
         <xmax>698.540314695083</xmax>
         <ymax>224.60020179797255</ymax>
      </bndbox>
   </object>
   <object>
      <name>table row</name>
      <pose>Frontal</pose>
      <truncated>0</truncated>
      <difficult>0</difficult>
      <occluded>0</occluded>
      <bndbox>
         <xmin>28.94661084171456</xmin>
         <ymin>224.60020179797255</ymin>
         <xmax>698.540314695083</xmax>
         <ymax>238.64873308788316</ymax>
      </bndbox>
   </object>
   <object>
      <name>table row</name>
      <pose>Frontal</pose>
      <truncated>0</truncated>
      <difficult>0</difficult>
      <occluded>0</occluded>
      <bndbox>
         <xmin>28.94661084171456</xmin>
         <ymin>238.64873308788316</ymin>
         <xmax>698.540314695083</xmax>
         <ymax>252.69726437779374</ymax>
      </bndbox>
   </object>
   <object>
      <name>table row</name>
      <pose>Frontal</pose>
      <truncated>0</truncated>
      <difficult>0</difficult>
      <occluded>0</occluded>
      <bndbox>
         <xmin>28.94661084171456</xmin>
         <ymin>252.69726437779374</ymin>
         <xmax>698.540314695083</xmax>
         <ymax>266.74579566770433</ymax>
      </bndbox>
   </object>
   <object>
      <name>table row</name>
      <pose>Frontal</pose>
      <truncated>0</truncated>
      <difficult>0</difficult>
      <occluded>0</occluded>
      <bndbox>
         <xmin>28.94661084171456</xmin>
         <ymin>266.74579566770433</ymin>
         <xmax>698.540314695083</xmax>
         <ymax>280.89139468216194</ymax>
      </bndbox>
   </object>
   <object>
      <name>table row</name>
      <pose>Frontal</pose>
      <truncated>0</truncated>
      <difficult>0</difficult>
      <occluded>0</occluded>
      <bndbox>
         <xmin>28.94661084171456</xmin>
         <ymin>280.89139468216194</ymin>
         <xmax>698.540314695083</xmax>
         <ymax>294.2042886434387</ymax>
      </bndbox>
   </object>
   <object>
      <name>table row</name>
      <pose>Frontal</pose>
      <truncated>0</truncated>
      <difficult>0</difficult>
      <occluded>0</occluded>
      <bndbox>
         <xmin>28.94661084171456</xmin>
         <ymin>294.2042886434387</ymin>
         <xmax>698.540314695083</xmax>
         <ymax>307.61425032926246</ymax>
      </bndbox>
   </object>
   <object>
      <name>table row</name>
      <pose>Frontal</pose>
      <truncated>0</truncated>
      <difficult>0</difficult>
      <occluded>0</occluded>
      <bndbox>
         <xmin>28.94661084171456</xmin>
         <ymin>307.61425032926246</ymin>
         <xmax>698.540314695083</xmax>
         <ymax>321.6627816191731</ymax>
      </bndbox>
   </object>
   <object>
      <name>table row</name>
      <pose>Frontal</pose>
      <truncated>0</truncated>
      <difficult>0</difficult>
      <occluded>0</occluded>
      <bndbox>
         <xmin>28.94661084171456</xmin>
         <ymin>321.6627816191731</ymin>
         <xmax>698.540314695083</xmax>
         <ymax>335.7113129090837</ymax>
      </bndbox>
   </object>
   <object>
      <name>table row</name>
      <pose>Frontal</pose>
      <truncated>0</truncated>
      <difficult>0</difficult>
      <occluded>0</occluded>
      <bndbox>
         <xmin>28.94661084171456</xmin>
         <ymin>335.7113129090837</ymin>
         <xmax>698.540314695083</xmax>
         <ymax>349.75984419899424</ymax>
      </bndbox>
   </object>
   <object>
      <name>table row</name>
      <pose>Frontal</pose>
      <truncated>0</truncated>
      <difficult>0</difficult>
      <occluded>0</occluded>
      <bndbox>
         <xmin>28.94661084171456</xmin>
         <ymin>349.75984419899424</ymin>
         <xmax>698.540314695083</xmax>
         <ymax>363.80837548890486</ymax>
      </bndbox>
   </object>
   <object>
      <name>table row</name>
      <pose>Frontal</pose>
      <truncated>0</truncated>
      <difficult>0</difficult>
      <occluded>0</occluded>
      <bndbox>
         <xmin>28.94661084171456</xmin>
         <ymin>363.80837548890486</ymin>
         <xmax>698.540314695083</xmax>
         <ymax>377.85690677881547</ymax>
      </bndbox>
   </object>
   <object>
      <name>table row</name>
      <pose>Frontal</pose>
      <truncated>0</truncated>
      <difficult>0</difficult>
      <occluded>0</occluded>
      <bndbox>
         <xmin>28.94661084171456</xmin>
         <ymin>377.85690677881547</ymin>
         <xmax>698.540314695083</xmax>
         <ymax>391.9054380687261</ymax>
      </bndbox>
   </object>
   <object>
      <name>table row</name>
      <pose>Frontal</pose>
      <truncated>0</truncated>
      <difficult>0</difficult>
      <occluded>0</occluded>
      <bndbox>
         <xmin>28.94661084171456</xmin>
         <ymin>391.9054380687261</ymin>
         <xmax>698.540314695083</xmax>
         <ymax>406.0510370831837</ymax>
      </bndbox>
   </object>
   <object>
      <name>table row</name>
      <pose>Frontal</pose>
      <truncated>0</truncated>
      <difficult>0</difficult>
      <occluded>0</occluded>
      <bndbox>
         <xmin>28.94661084171456</xmin>
         <ymin>406.0510370831837</ymin>
         <xmax>698.540314695083</xmax>
         <ymax>419.3639310444604</ymax>
      </bndbox>
   </object>
   <object>
      <name>table row</name>
      <pose>Frontal</pose>
      <truncated>0</truncated>
      <difficult>0</difficult>
      <occluded>0</occluded>
      <bndbox>
         <xmin>28.94661084171456</xmin>
         <ymin>419.3639310444604</ymin>
         <xmax>698.540314695083</xmax>
         <ymax>432.77389273028416</ymax>
      </bndbox>
   </object>
   <object>
      <name>table row</name>
      <pose>Frontal</pose>
      <truncated>0</truncated>
      <difficult>0</difficult>
      <occluded>0</occluded>
      <bndbox>
         <xmin>28.94661084171456</xmin>
         <ymin>432.77389273028416</ymin>
         <xmax>698.540314695083</xmax>
         <ymax>446.8224240201948</ymax>
      </bndbox>
   </object>
   <object>
      <name>table row</name>
      <pose>Frontal</pose>
      <truncated>0</truncated>
      <difficult>0</difficult>
      <occluded>0</occluded>
      <bndbox>
         <xmin>28.94661084171456</xmin>
         <ymin>446.8224240201948</ymin>
         <xmax>698.540314695083</xmax>
         <ymax>460.87095531010544</ymax>
      </bndbox>
   </object>
   <object>
      <name>table row</name>
      <pose>Frontal</pose>
      <truncated>0</truncated>
      <difficult>0</difficult>
      <occluded>0</occluded>
      <bndbox>
         <xmin>28.94661084171456</xmin>
         <ymin>460.87095531010544</ymin>
         <xmax>698.540314695083</xmax>
         <ymax>474.919486600016</ymax>
      </bndbox>
   </object>
   <object>
      <name>table row</name>
      <pose>Frontal</pose>
      <truncated>0</truncated>
      <difficult>0</difficult>
      <occluded>0</occluded>
      <bndbox>
         <xmin>28.94661084171456</xmin>
         <ymin>474.919486600016</ymin>
         <xmax>698.540314695083</xmax>
         <ymax>489.0650856144735</ymax>
      </bndbox>
   </object>
   <object>
      <name>table row</name>
      <pose>Frontal</pose>
      <truncated>0</truncated>
      <difficult>0</difficult>
      <occluded>0</occluded>
      <bndbox>
         <xmin>28.94661084171456</xmin>
         <ymin>489.0650856144735</ymin>
         <xmax>698.540314695083</xmax>
         <ymax>502.3779795757504</ymax>
      </bndbox>
   </object>
   <object>
      <name>table row</name>
      <pose>Frontal</pose>
      <truncated>0</truncated>
      <difficult>0</difficult>
      <occluded>0</occluded>
      <bndbox>
         <xmin>28.94661084171456</xmin>
         <ymin>502.3779795757504</ymin>
         <xmax>698.540314695083</xmax>
         <ymax>515.7879412615741</ymax>
      </bndbox>
   </object>
   <object>
      <name>table row</name>
      <pose>Frontal</pose>
      <truncated>0</truncated>
      <difficult>0</difficult>
      <occluded>0</occluded>
      <bndbox>
         <xmin>28.94661084171456</xmin>
         <ymin>515.7879412615741</ymin>
         <xmax>698.540314695083</xmax>
         <ymax>529.8364725514847</ymax>
      </bndbox>
   </object>
   <object>
      <name>table row</name>
      <pose>Frontal</pose>
      <truncated>0</truncated>
      <difficult>0</difficult>
      <occluded>0</occluded>
      <bndbox>
         <xmin>28.94661084171456</xmin>
         <ymin>529.8364725514847</ymin>
         <xmax>698.540314695083</xmax>
         <ymax>543.9820715659423</ymax>
      </bndbox>
   </object>
   <object>
      <name>table row</name>
      <pose>Frontal</pose>
      <truncated>0</truncated>
      <difficult>0</difficult>
      <occluded>0</occluded>
      <bndbox>
         <xmin>28.94661084171456</xmin>
         <ymin>543.9820715659423</ymin>
         <xmax>698.540314695083</xmax>
         <ymax>557.294965527219</ymax>
      </bndbox>
   </object>
   <object>
      <name>table row</name>
      <pose>Frontal</pose>
      <truncated>0</truncated>
      <difficult>0</difficult>
      <occluded>0</occluded>
      <bndbox>
         <xmin>28.94661084171456</xmin>
         <ymin>557.294965527219</ymin>
         <xmax>698.540314695083</xmax>
         <ymax>570.7049272130428</ymax>
      </bndbox>
   </object>
   <object>
      <name>table row</name>
      <pose>Frontal</pose>
      <truncated>0</truncated>
      <difficult>0</difficult>
      <occluded>0</occluded>
      <bndbox>
         <xmin>28.94661084171456</xmin>
         <ymin>570.7049272130428</ymin>
         <xmax>698.540314695083</xmax>
         <ymax>584.7534585029534</ymax>
      </bndbox>
   </object>
   <object>
      <name>table row</name>
      <pose>Frontal</pose>
      <truncated>0</truncated>
      <difficult>0</difficult>
      <occluded>0</occluded>
      <bndbox>
         <xmin>28.94661084171456</xmin>
         <ymin>584.7534585029534</ymin>
         <xmax>698.540314695083</xmax>
         <ymax>598.801989792864</ymax>
      </bndbox>
   </object>
   <object>
      <name>table row</name>
      <pose>Frontal</pose>
      <truncated>0</truncated>
      <difficult>0</difficult>
      <occluded>0</occluded>
      <bndbox>
         <xmin>28.94661084171456</xmin>
         <ymin>598.801989792864</ymin>
         <xmax>698.540314695083</xmax>
         <ymax>612.8505210827747</ymax>
      </bndbox>
   </object>
   <object>
      <name>table row</name>
      <pose>Frontal</pose>
      <truncated>0</truncated>
      <difficult>0</difficult>
      <occluded>0</occluded>
      <bndbox>
         <xmin>28.94661084171456</xmin>
         <ymin>612.8505210827747</ymin>
         <xmax>698.540314695083</xmax>
         <ymax>626.0408185664113</ymax>
      </bndbox>
   </object>
   <object>
      <name>table column</name>
      <pose>Frontal</pose>
      <truncated>0</truncated>
      <difficult>0</difficult>
      <occluded>0</occluded>
      <bndbox>
         <xmin>28.94661084171456</xmin>
         <ymin>29.362660842837045</ymin>
         <xmax>484.76261424409324</xmax>
         <ymax>626.0408185664113</ymax>
      </bndbox>
   </object>
   <object>
      <name>table column</name>
      <pose>Frontal</pose>
      <truncated>0</truncated>
      <difficult>0</difficult>
      <occluded>0</occluded>
      <bndbox>
         <xmin>484.76261424409324</xmin>
         <ymin>29.362660842837045</ymin>
         <xmax>589.1917788528696</xmax>
         <ymax>626.0408185664113</ymax>
      </bndbox>
   </object>
   <object>
      <name>table column</name>
      <pose>Frontal</pose>
      <truncated>0</truncated>
      <difficult>0</difficult>
      <occluded>0</occluded>
      <bndbox>
         <xmin>589.1917788528696</xmin>
         <ymin>29.362660842837045</ymin>
         <xmax>647.7920377105285</xmax>
         <ymax>626.0408185664113</ymax>
      </bndbox>
   </object>
   <object>
      <name>table column</name>
      <pose>Frontal</pose>
      <truncated>0</truncated>
      <difficult>0</difficult>
      <occluded>0</occluded>
      <bndbox>
         <xmin>647.7920377105285</xmin>
         <ymin>29.362660842837045</ymin>
         <xmax>698.540314695083</xmax>
         <ymax>626.0408185664113</ymax>
      </bndbox>
   </object>
</annotation>
