<?xml version="1.0" ?>
<annotation>
   <folder/>
   <filename>MET_2014_page_128_table_1.jpg</filename>
   <path>MET_2014_page_128_table_1.jpg</path>
   <source>
      <database>FinTabNet.c-Structure</database>
   </source>
   <size>
      <width>690</width>
      <height>380</height>
      <depth>3</depth>
   </size>
   <segmented>0</segmented>
   <object>
      <name>table</name>
      <pose>Frontal</pose>
      <truncated>0</truncated>
      <difficult>0</difficult>
      <occluded>0</occluded>
      <bndbox>
         <xmin>28.96969696969697</xmin>
         <ymin>28.506304191820504</ymin>
         <xmax>659.1102905273438</xmax>
         <ymax>348.51636420355896</ymax>
      </bndbox>
   </object>
   <object>
      <name>table column header</name>
      <pose>Frontal</pose>
      <truncated>0</truncated>
      <difficult>0</difficult>
      <occluded>0</occluded>
      <bndbox>
         <xmin>28.96969696969697</xmin>
         <ymin>28.506304191820504</ymin>
         <xmax>659.1102905273438</xmax>
         <ymax>43.30933326181736</ymax>
      </bndbox>
   </object>
   <object>
      <name>table row</name>
      <pose>Frontal</pose>
      <truncated>0</truncated>
      <difficult>0</difficult>
      <occluded>0</occluded>
      <bndbox>
         <xmin>28.96969696969697</xmin>
         <ymin>28.506304191820504</ymin>
         <xmax>659.1102905273438</xmax>
         <ymax>43.30933326181736</ymax>
      </bndbox>
   </object>
   <object>
      <name>table row</name>
      <pose>Frontal</pose>
      <truncated>0</truncated>
      <difficult>0</difficult>
      <occluded>0</occluded>
      <bndbox>
         <xmin>28.96969696969697</xmin>
         <ymin>43.30933326181736</ymin>
         <xmax>659.1102905273438</xmax>
         <ymax>98.86488881737291</ymax>
      </bndbox>
   </object>
   <object>
      <name>table row</name>
      <pose>Frontal</pose>
      <truncated>0</truncated>
      <difficult>0</difficult>
      <occluded>0</occluded>
      <bndbox>
         <xmin>28.96969696969697</xmin>
         <ymin>98.86488881737291</ymin>
         <xmax>659.1102905273438</xmax>
         <ymax>167.0467069991911</ymax>
      </bndbox>
   </object>
   <object>
      <name>table row</name>
      <pose>Frontal</pose>
      <truncated>0</truncated>
      <difficult>0</difficult>
      <occluded>0</occluded>
      <bndbox>
         <xmin>28.96969696969697</xmin>
         <ymin>167.0467069991911</ymin>
         <xmax>659.1102905273438</xmax>
         <ymax>209.97599992848404</ymax>
      </bndbox>
   </object>
   <object>
      <name>table row</name>
      <pose>Frontal</pose>
      <truncated>0</truncated>
      <difficult>0</difficult>
      <occluded>0</occluded>
      <bndbox>
         <xmin>28.96969696969697</xmin>
         <ymin>209.97599992848404</ymin>
         <xmax>659.1102905273438</xmax>
         <ymax>252.9052735916291</ymax>
      </bndbox>
   </object>
   <object>
      <name>table row</name>
      <pose>Frontal</pose>
      <truncated>0</truncated>
      <difficult>0</difficult>
      <occluded>0</occluded>
      <bndbox>
         <xmin>28.96969696969697</xmin>
         <ymin>252.9052735916291</ymin>
         <xmax>659.1102905273438</xmax>
         <ymax>295.8345472547743</ymax>
      </bndbox>
   </object>
   <object>
      <name>table row</name>
      <pose>Frontal</pose>
      <truncated>0</truncated>
      <difficult>0</difficult>
      <occluded>0</occluded>
      <bndbox>
         <xmin>28.96969696969697</xmin>
         <ymin>295.8345472547743</ymin>
         <xmax>659.1102905273438</xmax>
         <ymax>348.51636420355896</ymax>
      </bndbox>
   </object>
   <object>
      <name>table column</name>
      <pose>Frontal</pose>
      <truncated>0</truncated>
      <difficult>0</difficult>
      <occluded>0</occluded>
      <bndbox>
         <xmin>28.96969696969697</xmin>
         <ymin>28.506304191820504</ymin>
         <xmax>156.03334222658714</xmax>
         <ymax>348.51636420355896</ymax>
      </bndbox>
   </object>
   <object>
      <name>table column</name>
      <pose>Frontal</pose>
      <truncated>0</truncated>
      <difficult>0</difficult>
      <occluded>0</occluded>
      <bndbox>
         <xmin>156.03334222658714</xmin>
         <ymin>28.506304191820504</ymin>
         <xmax>659.1102905273438</xmax>
         <ymax>348.51636420355896</ymax>
      </bndbox>
   </object>
</annotation>
