<?xml version="1.0" ?>
<annotation>
   <folder/>
   <filename>MKC_2012_page_58_table_0.jpg</filename>
   <path>MKC_2012_page_58_table_0.jpg</path>
   <source>
      <database>FinTabNet.c-Structure</database>
   </source>
   <size>
      <width>629</width>
      <height>386</height>
      <depth>3</depth>
   </size>
   <segmented>0</segmented>
   <object>
      <name>table</name>
      <pose>Frontal</pose>
      <truncated>0</truncated>
      <difficult>0</difficult>
      <occluded>0</occluded>
      <bndbox>
         <xmin>3.757575757575751</xmin>
         <ymin>4.037977970007688</ymin>
         <xmax>623.4242436572758</xmax>
         <ymax>380.47162019363554</ymax>
      </bndbox>
   </object>
   <object>
      <name>table spanning cell</name>
      <pose>Frontal</pose>
      <truncated>0</truncated>
      <difficult>0</difficult>
      <occluded>0</occluded>
      <bndbox>
         <xmin>3.757575757575751</xmin>
         <ymin>4.037977970007688</ymin>
         <xmax>255.76769002278644</xmax>
         <ymax>35.15919340499724</ymax>
      </bndbox>
   </object>
   <object>
      <name>table spanning cell</name>
      <pose>Frontal</pose>
      <truncated>0</truncated>
      <difficult>0</difficult>
      <occluded>0</occluded>
      <bndbox>
         <xmin>255.76769002278644</xmin>
         <ymin>4.037977970007688</ymin>
         <xmax>477.10101071752683</xmax>
         <ymax>17.928437049942772</ymax>
      </bndbox>
   </object>
   <object>
      <name>table spanning cell</name>
      <pose>Frontal</pose>
      <truncated>0</truncated>
      <difficult>0</difficult>
      <occluded>0</occluded>
      <bndbox>
         <xmin>477.10101071752683</xmin>
         <ymin>4.037977970007688</ymin>
         <xmax>623.4242436572758</xmax>
         <ymax>17.928437049942772</ymax>
      </bndbox>
   </object>
   <object>
      <name>table projected row header</name>
      <pose>Frontal</pose>
      <truncated>0</truncated>
      <difficult>0</difficult>
      <occluded>0</occluded>
      <bndbox>
         <xmin>3.757575757575751</xmin>
         <ymin>35.15919340499724</ymin>
         <xmax>623.4242436572758</xmax>
         <ymax>50.36562671083391</ymax>
      </bndbox>
   </object>
   <object>
      <name>table projected row header</name>
      <pose>Frontal</pose>
      <truncated>0</truncated>
      <difficult>0</difficult>
      <occluded>0</occluded>
      <bndbox>
         <xmin>3.757575757575751</xmin>
         <ymin>184.85550497035786</ymin>
         <xmax>623.4242436572758</xmax>
         <ymax>199.9817622020991</ymax>
      </bndbox>
   </object>
   <object>
      <name>table projected row header</name>
      <pose>Frontal</pose>
      <truncated>0</truncated>
      <difficult>0</difficult>
      <occluded>0</occluded>
      <bndbox>
         <xmin>3.757575757575751</xmin>
         <ymin>327.36556267015857</ymin>
         <xmax>623.4242436572758</xmax>
         <ymax>355.27465851138334</ymax>
      </bndbox>
   </object>
   <object>
      <name>table column header</name>
      <pose>Frontal</pose>
      <truncated>0</truncated>
      <difficult>0</difficult>
      <occluded>0</occluded>
      <bndbox>
         <xmin>3.757575757575751</xmin>
         <ymin>4.037977970007688</ymin>
         <xmax>623.4242436572758</xmax>
         <ymax>35.15919340499724</ymax>
      </bndbox>
   </object>
   <object>
      <name>table row</name>
      <pose>Frontal</pose>
      <truncated>0</truncated>
      <difficult>0</difficult>
      <occluded>0</occluded>
      <bndbox>
         <xmin>3.757575757575751</xmin>
         <ymin>4.037977970007688</ymin>
         <xmax>623.4242436572758</xmax>
         <ymax>17.92844186647973</ymax>
      </bndbox>
   </object>
   <object>
      <name>table row</name>
      <pose>Frontal</pose>
      <truncated>0</truncated>
      <difficult>0</difficult>
      <occluded>0</occluded>
      <bndbox>
         <xmin>3.757575757575751</xmin>
         <ymin>17.92844186647973</ymin>
         <xmax>623.4242436572758</xmax>
         <ymax>35.15918858846027</ymax>
      </bndbox>
   </object>
   <object>
      <name>table row</name>
      <pose>Frontal</pose>
      <truncated>0</truncated>
      <difficult>0</difficult>
      <occluded>0</occluded>
      <bndbox>
         <xmin>3.757575757575751</xmin>
         <ymin>35.15918858846027</ymin>
         <xmax>623.4242436572758</xmax>
         <ymax>50.36562671083391</ymax>
      </bndbox>
   </object>
   <object>
      <name>table row</name>
      <pose>Frontal</pose>
      <truncated>0</truncated>
      <difficult>0</difficult>
      <occluded>0</occluded>
      <bndbox>
         <xmin>3.757575757575751</xmin>
         <ymin>50.36562671083391</ymin>
         <xmax>623.4242436572758</xmax>
         <ymax>62.99188933709655</ymax>
      </bndbox>
   </object>
   <object>
      <name>table row</name>
      <pose>Frontal</pose>
      <truncated>0</truncated>
      <difficult>0</difficult>
      <occluded>0</occluded>
      <bndbox>
         <xmin>3.757575757575751</xmin>
         <ymin>62.99188933709655</ymin>
         <xmax>623.4242436572758</xmax>
         <ymax>75.61815196335917</ymax>
      </bndbox>
   </object>
   <object>
      <name>table row</name>
      <pose>Frontal</pose>
      <truncated>0</truncated>
      <difficult>0</difficult>
      <occluded>0</occluded>
      <bndbox>
         <xmin>3.757575757575751</xmin>
         <ymin>75.61815196335917</ymin>
         <xmax>623.4242436572758</xmax>
         <ymax>88.24441458962178</ymax>
      </bndbox>
   </object>
   <object>
      <name>table row</name>
      <pose>Frontal</pose>
      <truncated>0</truncated>
      <difficult>0</difficult>
      <occluded>0</occluded>
      <bndbox>
         <xmin>3.757575757575751</xmin>
         <ymin>88.24441458962178</ymin>
         <xmax>623.4242436572758</xmax>
         <ymax>100.87067721588443</ymax>
      </bndbox>
   </object>
   <object>
      <name>table row</name>
      <pose>Frontal</pose>
      <truncated>0</truncated>
      <difficult>0</difficult>
      <occluded>0</occluded>
      <bndbox>
         <xmin>3.757575757575751</xmin>
         <ymin>100.87067721588443</ymin>
         <xmax>623.4242436572758</xmax>
         <ymax>113.49693984214704</ymax>
      </bndbox>
   </object>
   <object>
      <name>table row</name>
      <pose>Frontal</pose>
      <truncated>0</truncated>
      <difficult>0</difficult>
      <occluded>0</occluded>
      <bndbox>
         <xmin>3.757575757575751</xmin>
         <ymin>113.49693984214704</ymin>
         <xmax>623.4242436572758</xmax>
         <ymax>126.12320246840966</ymax>
      </bndbox>
   </object>
   <object>
      <name>table row</name>
      <pose>Frontal</pose>
      <truncated>0</truncated>
      <difficult>0</difficult>
      <occluded>0</occluded>
      <bndbox>
         <xmin>3.757575757575751</xmin>
         <ymin>126.12320246840966</ymin>
         <xmax>623.4242436572758</xmax>
         <ymax>138.7494650946723</ymax>
      </bndbox>
   </object>
   <object>
      <name>table row</name>
      <pose>Frontal</pose>
      <truncated>0</truncated>
      <difficult>0</difficult>
      <occluded>0</occluded>
      <bndbox>
         <xmin>3.757575757575751</xmin>
         <ymin>138.7494650946723</ymin>
         <xmax>623.4242436572758</xmax>
         <ymax>151.37572772093492</ymax>
      </bndbox>
   </object>
   <object>
      <name>table row</name>
      <pose>Frontal</pose>
      <truncated>0</truncated>
      <difficult>0</difficult>
      <occluded>0</occluded>
      <bndbox>
         <xmin>3.757575757575751</xmin>
         <ymin>151.37572772093492</ymin>
         <xmax>623.4242436572758</xmax>
         <ymax>166.68379958952312</ymax>
      </bndbox>
   </object>
   <object>
      <name>table row</name>
      <pose>Frontal</pose>
      <truncated>0</truncated>
      <difficult>0</difficult>
      <occluded>0</occluded>
      <bndbox>
         <xmin>3.757575757575751</xmin>
         <ymin>166.68379958952312</ymin>
         <xmax>623.4242436572758</xmax>
         <ymax>184.85550497035786</ymax>
      </bndbox>
   </object>
   <object>
      <name>table row</name>
      <pose>Frontal</pose>
      <truncated>0</truncated>
      <difficult>0</difficult>
      <occluded>0</occluded>
      <bndbox>
         <xmin>3.757575757575751</xmin>
         <ymin>184.85550497035786</ymin>
         <xmax>623.4242436572758</xmax>
         <ymax>199.98175256902522</ymax>
      </bndbox>
   </object>
   <object>
      <name>table row</name>
      <pose>Frontal</pose>
      <truncated>0</truncated>
      <difficult>0</difficult>
      <occluded>0</occluded>
      <bndbox>
         <xmin>3.757575757575751</xmin>
         <ymin>199.98175256902522</ymin>
         <xmax>623.4242436572758</xmax>
         <ymax>212.6080151952878</ymax>
      </bndbox>
   </object>
   <object>
      <name>table row</name>
      <pose>Frontal</pose>
      <truncated>0</truncated>
      <difficult>0</difficult>
      <occluded>0</occluded>
      <bndbox>
         <xmin>3.757575757575751</xmin>
         <ymin>212.6080151952878</ymin>
         <xmax>623.4242436572758</xmax>
         <ymax>225.23428745462434</ymax>
      </bndbox>
   </object>
   <object>
      <name>table row</name>
      <pose>Frontal</pose>
      <truncated>0</truncated>
      <difficult>0</difficult>
      <occluded>0</occluded>
      <bndbox>
         <xmin>3.757575757575751</xmin>
         <ymin>225.23428745462434</ymin>
         <xmax>623.4242436572758</xmax>
         <ymax>237.86055008088698</ymax>
      </bndbox>
   </object>
   <object>
      <name>table row</name>
      <pose>Frontal</pose>
      <truncated>0</truncated>
      <difficult>0</difficult>
      <occluded>0</occluded>
      <bndbox>
         <xmin>3.757575757575751</xmin>
         <ymin>237.86055008088698</ymin>
         <xmax>623.4242436572758</xmax>
         <ymax>250.48681270714965</ymax>
      </bndbox>
   </object>
   <object>
      <name>table row</name>
      <pose>Frontal</pose>
      <truncated>0</truncated>
      <difficult>0</difficult>
      <occluded>0</occluded>
      <bndbox>
         <xmin>3.757575757575751</xmin>
         <ymin>250.48681270714965</ymin>
         <xmax>623.4242436572758</xmax>
         <ymax>263.1130753334122</ymax>
      </bndbox>
   </object>
   <object>
      <name>table row</name>
      <pose>Frontal</pose>
      <truncated>0</truncated>
      <difficult>0</difficult>
      <occluded>0</occluded>
      <bndbox>
         <xmin>3.757575757575751</xmin>
         <ymin>263.1130753334122</ymin>
         <xmax>623.4242436572758</xmax>
         <ymax>275.73933795967486</ymax>
      </bndbox>
   </object>
   <object>
      <name>table row</name>
      <pose>Frontal</pose>
      <truncated>0</truncated>
      <difficult>0</difficult>
      <occluded>0</occluded>
      <bndbox>
         <xmin>3.757575757575751</xmin>
         <ymin>275.73933795967486</ymin>
         <xmax>623.4242436572758</xmax>
         <ymax>291.0474098282631</ymax>
      </bndbox>
   </object>
   <object>
      <name>table row</name>
      <pose>Frontal</pose>
      <truncated>0</truncated>
      <difficult>0</difficult>
      <occluded>0</occluded>
      <bndbox>
         <xmin>3.757575757575751</xmin>
         <ymin>291.0474098282631</ymin>
         <xmax>623.4242436572758</xmax>
         <ymax>309.0372909391769</ymax>
      </bndbox>
   </object>
   <object>
      <name>table row</name>
      <pose>Frontal</pose>
      <truncated>0</truncated>
      <difficult>0</difficult>
      <occluded>0</occluded>
      <bndbox>
         <xmin>3.757575757575751</xmin>
         <ymin>309.0372909391769</ymin>
         <xmax>623.4242436572758</xmax>
         <ymax>327.36556267015857</ymax>
      </bndbox>
   </object>
   <object>
      <name>table row</name>
      <pose>Frontal</pose>
      <truncated>0</truncated>
      <difficult>0</difficult>
      <occluded>0</occluded>
      <bndbox>
         <xmin>3.757575757575751</xmin>
         <ymin>327.36556267015857</ymin>
         <xmax>623.4242436572758</xmax>
         <ymax>355.27465851138334</ymax>
      </bndbox>
   </object>
   <object>
      <name>table row</name>
      <pose>Frontal</pose>
      <truncated>0</truncated>
      <difficult>0</difficult>
      <occluded>0</occluded>
      <bndbox>
         <xmin>3.757575757575751</xmin>
         <ymin>355.27465851138334</ymin>
         <xmax>623.4242436572758</xmax>
         <ymax>367.900921137646</ymax>
      </bndbox>
   </object>
   <object>
      <name>table row</name>
      <pose>Frontal</pose>
      <truncated>0</truncated>
      <difficult>0</difficult>
      <occluded>0</occluded>
      <bndbox>
         <xmin>3.757575757575751</xmin>
         <ymin>367.900921137646</ymin>
         <xmax>623.4242436572758</xmax>
         <ymax>380.47162019363554</ymax>
      </bndbox>
   </object>
   <object>
      <name>table column</name>
      <pose>Frontal</pose>
      <truncated>0</truncated>
      <difficult>0</difficult>
      <occluded>0</occluded>
      <bndbox>
         <xmin>3.757575757575751</xmin>
         <ymin>4.037977970007688</ymin>
         <xmax>255.76769965586033</xmax>
         <ymax>380.47162019363554</ymax>
      </bndbox>
   </object>
   <object>
      <name>table column</name>
      <pose>Frontal</pose>
      <truncated>0</truncated>
      <difficult>0</difficult>
      <occluded>0</occluded>
      <bndbox>
         <xmin>255.76769965586033</xmin>
         <ymin>4.037977970007688</ymin>
         <xmax>382.0555549390388</xmax>
         <ymax>380.47162019363554</ymax>
      </bndbox>
   </object>
   <object>
      <name>table column</name>
      <pose>Frontal</pose>
      <truncated>0</truncated>
      <difficult>0</difficult>
      <occluded>0</occluded>
      <bndbox>
         <xmin>382.0555549390388</xmin>
         <ymin>4.037977970007688</ymin>
         <xmax>477.10101071752683</xmax>
         <ymax>380.47162019363554</ymax>
      </bndbox>
   </object>
   <object>
      <name>table column</name>
      <pose>Frontal</pose>
      <truncated>0</truncated>
      <difficult>0</difficult>
      <occluded>0</occluded>
      <bndbox>
         <xmin>477.10101071752683</xmin>
         <ymin>4.037977970007688</ymin>
         <xmax>571.4494943329781</xmax>
         <ymax>380.47162019363554</ymax>
      </bndbox>
   </object>
   <object>
      <name>table column</name>
      <pose>Frontal</pose>
      <truncated>0</truncated>
      <difficult>0</difficult>
      <occluded>0</occluded>
      <bndbox>
         <xmin>571.4494943329781</xmin>
         <ymin>4.037977970007688</ymin>
         <xmax>623.4242436572758</xmax>
         <ymax>380.47162019363554</ymax>
      </bndbox>
   </object>
</annotation>
