<?xml version="1.0" ?>
<annotation>
   <folder/>
   <filename>WST_2008_page_66_table_0.jpg</filename>
   <path>WST_2008_page_66_table_0.jpg</path>
   <source>
      <database>FinTabNet.c-Structure</database>
   </source>
   <size>
      <width>515</width>
      <height>187</height>
      <depth>3</depth>
   </size>
   <segmented>0</segmented>
   <object>
      <name>table</name>
      <pose>Frontal</pose>
      <truncated>0</truncated>
      <difficult>0</difficult>
      <occluded>0</occluded>
      <bndbox>
         <xmin>4.454441417347297</xmin>
         <ymin>3.8473128501814955</ymin>
         <xmax>509.10742804016724</xmax>
         <ymax>181.3425564236111</ymax>
      </bndbox>
   </object>
   <object>
      <name>table spanning cell</name>
      <pose>Frontal</pose>
      <truncated>0</truncated>
      <difficult>0</difficult>
      <occluded>0</occluded>
      <bndbox>
         <xmin>4.454441417347297</xmin>
         <ymin>3.8473128501814955</ymin>
         <xmax>228.49008980182685</xmax>
         <ymax>33.58230005129418</ymax>
      </bndbox>
   </object>
   <object>
      <name>table spanning cell</name>
      <pose>Frontal</pose>
      <truncated>0</truncated>
      <difficult>0</difficult>
      <occluded>0</occluded>
      <bndbox>
         <xmin>228.49008980182685</xmin>
         <ymin>3.8473128501814955</ymin>
         <xmax>371.1126425386679</xmax>
         <ymax>18.39290765319207</ymax>
      </bndbox>
   </object>
   <object>
      <name>table spanning cell</name>
      <pose>Frontal</pose>
      <truncated>0</truncated>
      <difficult>0</difficult>
      <occluded>0</occluded>
      <bndbox>
         <xmin>371.1126425386679</xmin>
         <ymin>3.8473128501814955</ymin>
         <xmax>509.10742804016724</xmax>
         <ymax>18.39290765319207</ymax>
      </bndbox>
   </object>
   <object>
      <name>table projected row header</name>
      <pose>Frontal</pose>
      <truncated>0</truncated>
      <difficult>0</difficult>
      <occluded>0</occluded>
      <bndbox>
         <xmin>4.454441417347297</xmin>
         <ymin>33.58230005129418</ymin>
         <xmax>509.10742804016724</xmax>
         <ymax>48.42833116319443</ymax>
      </bndbox>
   </object>
   <object>
      <name>table column header</name>
      <pose>Frontal</pose>
      <truncated>0</truncated>
      <difficult>0</difficult>
      <occluded>0</occluded>
      <bndbox>
         <xmin>4.454441417347297</xmin>
         <ymin>3.8473128501814955</ymin>
         <xmax>509.10742804016724</xmax>
         <ymax>33.58230005129418</ymax>
      </bndbox>
   </object>
   <object>
      <name>table row</name>
      <pose>Frontal</pose>
      <truncated>0</truncated>
      <difficult>0</difficult>
      <occluded>0</occluded>
      <bndbox>
         <xmin>4.454441417347297</xmin>
         <ymin>3.8473128501814955</ymin>
         <xmax>509.10742804016724</xmax>
         <ymax>18.392902836655125</ymax>
      </bndbox>
   </object>
   <object>
      <name>table row</name>
      <pose>Frontal</pose>
      <truncated>0</truncated>
      <difficult>0</difficult>
      <occluded>0</occluded>
      <bndbox>
         <xmin>4.454441417347297</xmin>
         <ymin>18.392902836655125</ymin>
         <xmax>509.10742804016724</xmax>
         <ymax>33.582295234757225</ymax>
      </bndbox>
   </object>
   <object>
      <name>table row</name>
      <pose>Frontal</pose>
      <truncated>0</truncated>
      <difficult>0</difficult>
      <occluded>0</occluded>
      <bndbox>
         <xmin>4.454441417347297</xmin>
         <ymin>33.582295234757225</ymin>
         <xmax>509.10742804016724</xmax>
         <ymax>48.428326346657485</ymax>
      </bndbox>
   </object>
   <object>
      <name>table row</name>
      <pose>Frontal</pose>
      <truncated>0</truncated>
      <difficult>0</difficult>
      <occluded>0</occluded>
      <bndbox>
         <xmin>4.454441417347297</xmin>
         <ymin>48.428326346657485</ymin>
         <xmax>509.10742804016724</xmax>
         <ymax>62.89990060979668</ymax>
      </bndbox>
   </object>
   <object>
      <name>table row</name>
      <pose>Frontal</pose>
      <truncated>0</truncated>
      <difficult>0</difficult>
      <occluded>0</occluded>
      <bndbox>
         <xmin>4.454441417347297</xmin>
         <ymin>62.89990060979668</ymin>
         <xmax>509.10742804016724</xmax>
         <ymax>77.4491607974274</ymax>
      </bndbox>
   </object>
   <object>
      <name>table row</name>
      <pose>Frontal</pose>
      <truncated>0</truncated>
      <difficult>0</difficult>
      <occluded>0</occluded>
      <bndbox>
         <xmin>4.454441417347297</xmin>
         <ymin>77.4491607974274</ymin>
         <xmax>509.10742804016724</xmax>
         <ymax>91.96046185734296</ymax>
      </bndbox>
   </object>
   <object>
      <name>table row</name>
      <pose>Frontal</pose>
      <truncated>0</truncated>
      <difficult>0</difficult>
      <occluded>0</occluded>
      <bndbox>
         <xmin>4.454441417347297</xmin>
         <ymin>91.96046185734296</ymin>
         <xmax>509.10742804016724</xmax>
         <ymax>106.4717629172585</ymax>
      </bndbox>
   </object>
   <object>
      <name>table row</name>
      <pose>Frontal</pose>
      <truncated>0</truncated>
      <difficult>0</difficult>
      <occluded>0</occluded>
      <bndbox>
         <xmin>4.454441417347297</xmin>
         <ymin>106.4717629172585</ymin>
         <xmax>509.10742804016724</xmax>
         <ymax>121.02101828835225</ymax>
      </bndbox>
   </object>
   <object>
      <name>table row</name>
      <pose>Frontal</pose>
      <truncated>0</truncated>
      <difficult>0</difficult>
      <occluded>0</occluded>
      <bndbox>
         <xmin>4.454441417347297</xmin>
         <ymin>121.02101828835225</ymin>
         <xmax>509.10742804016724</xmax>
         <ymax>135.83595383769332</ymax>
      </bndbox>
   </object>
   <object>
      <name>table row</name>
      <pose>Frontal</pose>
      <truncated>0</truncated>
      <difficult>0</difficult>
      <occluded>0</occluded>
      <bndbox>
         <xmin>4.454441417347297</xmin>
         <ymin>135.83595383769332</ymin>
         <xmax>509.10742804016724</xmax>
         <ymax>158.85676559294112</ymax>
      </bndbox>
   </object>
   <object>
      <name>table row</name>
      <pose>Frontal</pose>
      <truncated>0</truncated>
      <difficult>0</difficult>
      <occluded>0</occluded>
      <bndbox>
         <xmin>4.454441417347297</xmin>
         <ymin>158.85676559294112</ymin>
         <xmax>509.10742804016724</xmax>
         <ymax>181.3425564236111</ymax>
      </bndbox>
   </object>
   <object>
      <name>table column</name>
      <pose>Frontal</pose>
      <truncated>0</truncated>
      <difficult>0</difficult>
      <occluded>0</occluded>
      <bndbox>
         <xmin>4.454441417347297</xmin>
         <ymin>3.8473128501814955</ymin>
         <xmax>228.4900801687529</xmax>
         <ymax>181.3425564236111</ymax>
      </bndbox>
   </object>
   <object>
      <name>table column</name>
      <pose>Frontal</pose>
      <truncated>0</truncated>
      <difficult>0</difficult>
      <occluded>0</occluded>
      <bndbox>
         <xmin>228.4900801687529</xmin>
         <ymin>3.8473128501814955</ymin>
         <xmax>309.65592370852073</xmax>
         <ymax>181.3425564236111</ymax>
      </bndbox>
   </object>
   <object>
      <name>table column</name>
      <pose>Frontal</pose>
      <truncated>0</truncated>
      <difficult>0</difficult>
      <occluded>0</occluded>
      <bndbox>
         <xmin>309.65592370852073</xmin>
         <ymin>3.8473128501814955</ymin>
         <xmax>371.11262327252007</xmax>
         <ymax>181.3425564236111</ymax>
      </bndbox>
   </object>
   <object>
      <name>table column</name>
      <pose>Frontal</pose>
      <truncated>0</truncated>
      <difficult>0</difficult>
      <occluded>0</occluded>
      <bndbox>
         <xmin>371.11262327252007</xmin>
         <ymin>3.8473128501814955</ymin>
         <xmax>456.5464098381274</xmax>
         <ymax>181.3425564236111</ymax>
      </bndbox>
   </object>
   <object>
      <name>table column</name>
      <pose>Frontal</pose>
      <truncated>0</truncated>
      <difficult>0</difficult>
      <occluded>0</occluded>
      <bndbox>
         <xmin>456.5464098381274</xmin>
         <ymin>3.8473128501814955</ymin>
         <xmax>509.10742804016724</xmax>
         <ymax>181.3425564236111</ymax>
      </bndbox>
   </object>
</annotation>
